gradescope/__init__.py
gradescope/api.py
gradescope/exceptions.py
gradescope/macros.py
gradescope/raw_util.py
gradescope/util.py
gradescope/version.py
gradescope-0.1.2.dist-info/LICENSE
gradescope-0.1.2.dist-info/METADATA
gradescope-0.1.2.dist-info/WHEEL
gradescope-0.1.2.dist-info/top_level.txt
gradescope-0.1.2.dist-info/RECORD
